sonicwall_api_client/__init__.py
sonicwall_api_client/sonicwall_api_client.py
sonicwall_api_client-1.0.5.dist-info/licenses/LICENSE
sonicwall_api_client-1.0.5.dist-info/METADATA
sonicwall_api_client-1.0.5.dist-info/WHEEL
sonicwall_api_client-1.0.5.dist-info/top_level.txt
sonicwall_api_client-1.0.5.dist-info/RECORD
