Metadata-Version: 2.4
Name: sonicwall-api-client
Version: 1.0.5
Summary: Simple Python client for SonicWall SonicOS REST API (with HTTP Digest Auth).
Home-page: https://github.com/Samuel-Berset/sonicwall-api-client
Author: Samuel Berset
Author-email: your.email@example.com
Classifier: Programming Language :: Python :: 3
Classifier: License :: OSI Approved :: MIT License
Classifier: Operating System :: OS Independent
Classifier: Development Status :: 4 - Beta
Classifier: Intended Audience :: Developers
Classifier: Topic :: System :: Networking
Requires-Python: >=3.9
License-File: LICENSE
Requires-Dist: requests>=2.25
Requires-Dist: urllib3>=1.26
Dynamic: author
Dynamic: author-email
Dynamic: classifier
Dynamic: description
Dynamic: description-content-type
Dynamic: home-page
Dynamic: license-file
Dynamic: requires-dist
Dynamic: requires-python
Dynamic: summary
